kunteksto/.flaskenv
kunteksto/__init__.py
kunteksto/analyze.py
kunteksto/catalogmgr.py
kunteksto/generate.py
kunteksto/kunteksto.bat
kunteksto/kunteksto.py
kunteksto/kunteksto.sh
kunteksto/kunteksto_old.py
kunteksto/modeledit.py
kunteksto/models.py
kunteksto/recordedit.py
kunteksto-2.1.0.data/data/LICENSE.txt
kunteksto-2.1.0.data/data/README.md
kunteksto-2.1.0.data/data/kunteksto.conf
kunteksto-2.1.0.data/data/catalogs/Kunteksto_catalog.xml
kunteksto-2.1.0.data/data/example_data/Demo.csv
kunteksto-2.1.0.data/data/example_data/Demo2.csv
kunteksto-2.1.0.data/data/example_data/Demo3.csv
kunteksto-2.1.0.data/data/example_data/Demo_info.pdf
kunteksto-2.1.0.data/data/s3model/dm-description.xsl
kunteksto-2.1.0.data/data/s3model/s3model.owl
kunteksto-2.1.0.data/data/s3model/s3model_3_1_0.rdf
kunteksto-2.1.0.data/data/s3model/s3model_3_1_0.xsd
kunteksto-2.1.0.data/data/s3model/s3model_3_1_0.xsl
kunteksto-2.1.0.data/data/utils/datastats.py
kunteksto-2.1.0.data/data/utils/db_setup.py
kunteksto-2.1.0.dist-info/LICENSE.txt
kunteksto-2.1.0.dist-info/METADATA
kunteksto-2.1.0.dist-info/WHEEL
kunteksto-2.1.0.dist-info/entry_points.txt
kunteksto-2.1.0.dist-info/top_level.txt
kunteksto-2.1.0.dist-info/RECORD
