Metadata-Version: 2.1
Name: kunteksto
Version: 2.1.0
Summary: The tool to translate your CSV data files into RDF, XML and JSON with full semantics and syntactic validation.
Home-page: https://datainsights.tech/
Author: Timothy W. Cook
Author-email: tim@datainsights.tech
License: UNKNOWN
Download-URL: https://github.com/DataInsightsInc/Kunteksto/archive/2.1.0.tar.gz
Keywords: context rdf xml machine learning data-centric semantic interoperability semantics
Platform: UNKNOWN
Classifier: Development Status :: 5 - Production/Stable
Classifier: Intended Audience :: Customer Service
Classifier: Intended Audience :: Developers
Classifier: Intended Audience :: Education
Classifier: Intended Audience :: End Users/Desktop
Classifier: Intended Audience :: Financial and Insurance Industry
Classifier: Intended Audience :: Healthcare Industry
Classifier: Intended Audience :: Information Technology
Classifier: Intended Audience :: Legal Industry
Classifier: Intended Audience :: Manufacturing
Classifier: Intended Audience :: Other Audience
Classifier: Intended Audience :: Religion
Classifier: Intended Audience :: Science/Research
Classifier: Intended Audience :: System Administrators
Classifier: Intended Audience :: Telecommunications Industry
Classifier: License :: OSI Approved :: Apache Software License
Classifier: Programming Language :: Python :: 3 :: Only
Classifier: Topic :: Scientific/Engineering :: Information Analysis
Requires-Python: >=3.7
Requires-Dist: agraph-python
Requires-Dist: basexclient
Requires-Dist: click
Requires-Dist: requests
Requires-Dist: lxml
Requires-Dist: shortuuid
Requires-Dist: sphinx
Requires-Dist: sphinx-rtd-theme
Requires-Dist: ujson
Requires-Dist: xmltodict
Requires-Dist: cuid
Requires-Dist: flask
Requires-Dist: flask-admin
Requires-Dist: flask-sqlalchemy
Requires-Dist: flask-babelex
Requires-Dist: sqlalchemy-utils
Requires-Dist: python-dotenv
